yumako/__init__.py
yumako/args.py
yumako/cache.py
yumako/env.py
yumako/fstore.py.tbd
yumako/jsondot.py.tbd
yumako/lru.py
yumako/state.py
yumako/template.py
yumako/time.py
yumako-0.1.37.dist-info/METADATA
yumako-0.1.37.dist-info/WHEEL
yumako-0.1.37.dist-info/licenses/LICENSE
yumako-0.1.37.dist-info/RECORD
