Metadata-Version: 2.4
Name: yumako
Version: 0.1.37
Summary: Vanilla python utilities, for humans.
License-Expression: MIT
License-File: LICENSE
Keywords: util,vanilla,for humans
Author: Nanw1103
Author-email: nanw1103@gmail.com
Requires-Python: >=3.9
Classifier: Development Status :: 4 - Beta
Classifier: Intended Audience :: Developers
Classifier: License :: OSI Approved :: MIT License
Classifier: Programming Language :: Python :: 3
